README.rst
setup.cfg
setup.py
twhst/__init__.py
twhst/admin.py
twhst/dictionary.py
twhst/models.py
twhst/rules.py
twhst/tests.py
twhst/utils.py
twhst/views.py
twhst.egg-info/PKG-INFO
twhst.egg-info/SOURCES.txt
twhst.egg-info/dependency_links.txt
twhst.egg-info/entry_points.txt
twhst.egg-info/not-zip-safe
twhst.egg-info/requires.txt
twhst.egg-info/top_level.txt
twhst/management/__init__.py
twhst/management/commands/__init__.py
twhst/management/commands/search_do.py