Metadata-Version: 1.0
Name: twhst
Version: 0.3
Summary: Follow and store tweets from twitter
Home-page: http://github.com/codesyntax/twhst
Author: Aitzol Naberan
Author-email: anaberan@codesyntax.com
License: GPL
Keywords: twitter
Platform: UNKNOWN
